grawlix/__init__.py
grawlix/__main__.py
grawlix/arguments.py
grawlix/book.py
grawlix/config.py
grawlix/encryption.py
grawlix/exceptions.py
grawlix/logging.py
grawlix/assets/errors/access_denied.txt
grawlix/assets/errors/data_not_found.txt
grawlix/assets/errors/invalid_url.txt
grawlix/assets/errors/source_not_authenticated.txt
grawlix/assets/errors/throttle.txt
grawlix/output/__init__.py
grawlix/output/acsm.py
grawlix/output/cbz.py
grawlix/output/epub.py
grawlix/output/output_format.py
grawlix/output/metadata/__init__.py
grawlix/output/metadata/comicinfo.py
grawlix/sources/__init__.py
grawlix/sources/dcuniverseinfinite.py
grawlix/sources/ereolen.py
grawlix/sources/fanfictionnet.py
grawlix/sources/flipp.py
grawlix/sources/internet_archive.py
grawlix/sources/mangaplus.py
grawlix/sources/marvel.py
grawlix/sources/nextory.py
grawlix/sources/royal_road.py
grawlix/sources/saxo.py
grawlix/sources/source.py
grawlix/sources/storytel.py
grawlix/sources/webtoons.py
grawlix/utils/__init__.py
grawlix-0.2.1.dist-info/LICENSE
grawlix-0.2.1.dist-info/METADATA
grawlix-0.2.1.dist-info/WHEEL
grawlix-0.2.1.dist-info/entry_points.txt
grawlix-0.2.1.dist-info/top_level.txt
grawlix-0.2.1.dist-info/RECORD
