Metadata-Version: 2.1
Name: grawlix
Version: 0.2.1
Summary: CLI tool for downloading ebooks
Author-email: Joakim Holm <mail@joakimholm.xyz>
Project-URL: Homepage, https://github.com/jo1gi/grawlix
Project-URL: Bugtracker, https://github.com/jo1gi/grawlix/issues
Keywords: ebook,cli,downloader
Classifier: Programming Language :: Python :: 3
Classifier: License :: OSI Approved :: GNU General Public License v3 (GPLv3)
License-File: LICENSE
Requires-Dist: appdirs
Requires-Dist: beautifulsoup4
Requires-Dist: blackboxprotobuf
Requires-Dist: EbookLib
Requires-Dist: httpx
Requires-Dist: importlib-resources
Requires-Dist: lxml
Requires-Dist: pycryptodome
Requires-Dist: rich
Requires-Dist: tomli
